{
  "batch": 4,
  "generated_utc": "2026-07-13T23:57:58.843992+00:00",
  "reference_date": "2026-07-12",
  "fame_min": 70,
  "fame_range_in_batch": [
    79.47,
    80.51
  ],
  "count": 40,
  "schema": {
    "description": "Research each player's status as of 2026-07-12 and fill these fields. Do NOT change id or name. Save the completed file(s) as data/research_patches/patch_NN.json with the same {id, ...} objects.",
    "fields": {
      "id": "int - players_db id, unchanged (join key, do not edit)",
      "name": "string - unchanged, for human reference",
      "status": "'active' or 'retired'",
      "current_team": "the club's COMMON name as of July 2026 (e.g. 'Real Madrid', 'Inter Miami', 'Al-Nassr'). For a RETIRED player, their LAST professional club. Name normalisation to the app's official club string happens automatically at apply time -- just give the common name.",
      "league": "for ACTIVE players, one of known_leagues below (the club's current league). For RETIRED players LEAVE THIS OUT / null -- their last league is kept automatically; do NOT write 'Retired'.",
      "market_value_eur": "integer euros, 0..300000000; use 0 for retired players",
      "retired_year": "integer year if retired, otherwise null"
    },
    "known_leagues": [
      "Premier League",
      "La Liga",
      "Serie A",
      "Bundesliga",
      "Ligue 1"
    ],
    "market_value_bounds_eur": [
      0,
      300000000
    ],
    "notes": [
      "current_team is normalised at apply time; unresolvable clubs are logged to research_patches/unresolved_clubs.json and skipped (other fields still apply).",
      "league is never set to 'Retired' or any new string -- retirement is carried by status + retired_year."
    ]
  },
  "players": [
    {
      "id": 1600032,
      "name": "Rivaldo",
      "nationality": "Brazil",
      "position": "Attack",
      "current_team": "Mogi Mirim Esporte Clube",
      "market_value": 0,
      "fame_score": 80.51,
      "birth_year": 1972
    },
    {
      "id": 39152,
      "name": "Radamel Falcao",
      "nationality": "Colombia",
      "position": "Attack",
      "current_team": "Millonarios Fc",
      "market_value": 500000,
      "fame_score": 80.47,
      "birth_year": 1986
    },
    {
      "id": 69751,
      "name": "Jordi Alba",
      "nationality": "Spain",
      "position": "Defender",
      "current_team": "Inter Miami",
      "market_value": 0,
      "fame_score": 80.35,
      "birth_year": 1989
    },
    {
      "id": 203655,
      "name": "Cafú",
      "nationality": "Portugal",
      "position": "Midfield",
      "current_team": "Kasimpasa",
      "market_value": 600000,
      "fame_score": 80.34,
      "birth_year": 1993
    },
    {
      "id": 80,
      "name": "Tom Starke",
      "nationality": "Germany",
      "position": "Goalkeeper",
      "current_team": "FC Bayern München",
      "market_value": 0,
      "fame_score": 80.26,
      "birth_year": 1981
    },
    {
      "id": 369081,
      "name": "Federico Valverde",
      "nationality": "Uruguay",
      "position": "Midfield",
      "current_team": "Real Madrid Club de Fútbol",
      "market_value": 120000000,
      "fame_score": 80.25,
      "birth_year": 1998
    },
    {
      "id": 616341,
      "name": "Nuno Mendes",
      "nationality": "Portugal",
      "position": "Defender",
      "current_team": "Paris Saint-Germain Football Club",
      "market_value": 75000000,
      "fame_score": 80.24,
      "birth_year": 2002
    },
    {
      "id": 1600033,
      "name": "Pepe",
      "nationality": "Portugal",
      "position": "Defender",
      "current_team": "FC Porto",
      "market_value": 0,
      "fame_score": 80.22,
      "birth_year": 1983
    },
    {
      "id": 580195,
      "name": "Jamal Musiala",
      "nationality": "Germany",
      "position": "Midfield",
      "current_team": "FC Bayern München",
      "market_value": 130000000,
      "fame_score": 80.2,
      "birth_year": 2003
    },
    {
      "id": 35207,
      "name": "Marco Reus",
      "nationality": "Germany",
      "position": "Midfield",
      "current_team": "LA Galaxy",
      "market_value": 4000000,
      "fame_score": 80.19,
      "birth_year": 1989
    },
    {
      "id": 636688,
      "name": "Alejandro Balde",
      "nationality": "Spain",
      "position": "Defender",
      "current_team": "Futbol Club Barcelona",
      "market_value": 60000000,
      "fame_score": 80.18,
      "birth_year": 2003
    },
    {
      "id": 29035,
      "name": "Ederson",
      "nationality": "Brazil",
      "position": "Goalkeeper",
      "current_team": "Fenerbahce",
      "market_value": 20000000,
      "fame_score": 80.17,
      "birth_year": 1993
    },
    {
      "id": 607854,
      "name": "Éderson",
      "nationality": "Brazil",
      "position": "Midfield",
      "current_team": "Atalanta Bergamasca Calcio S.p.a.",
      "market_value": 45000000,
      "fame_score": 80.17,
      "birth_year": 1999
    },
    {
      "id": 17965,
      "name": "Hugo Lloris",
      "nationality": "France",
      "position": "Goalkeeper",
      "current_team": "Los Angeles Fc",
      "market_value": 1000000,
      "fame_score": 80.16,
      "birth_year": 1986
    },
    {
      "id": 1600034,
      "name": "Romario",
      "nationality": "Brazil",
      "position": "Attack",
      "current_team": "America Rj",
      "market_value": 0,
      "fame_score": 80.16,
      "birth_year": 1966
    },
    {
      "id": 937958,
      "name": "Lamine Yamal",
      "nationality": "Spain",
      "position": "Attack",
      "current_team": "Futbol Club Barcelona",
      "market_value": 200000000,
      "fame_score": 80.14,
      "birth_year": 2007
    },
    {
      "id": 315853,
      "name": "Alessandro Bastoni",
      "nationality": "Italy",
      "position": "Defender",
      "current_team": "Football Club Internazionale Milano S.p.A.",
      "market_value": 70000000,
      "fame_score": 80.1,
      "birth_year": 1999
    },
    {
      "id": 1600035,
      "name": "Michael Ballack",
      "nationality": "Germany",
      "position": "Midfield",
      "current_team": "Bayer 04 Leverkusen Fußball",
      "market_value": 0,
      "fame_score": 80.1,
      "birth_year": 1976
    },
    {
      "id": 1600036,
      "name": "Patrick Vieira",
      "nationality": "France",
      "position": "Midfield",
      "current_team": "Manchester City Football Club",
      "market_value": 0,
      "fame_score": 79.99,
      "birth_year": 1976
    },
    {
      "id": 5658,
      "name": "Petr Cech",
      "nationality": "Czech Republic",
      "position": "Goalkeeper",
      "current_team": "Arsenal Football Club",
      "market_value": 0,
      "fame_score": 79.92,
      "birth_year": 1982
    },
    {
      "id": 1005649,
      "name": "Murillo",
      "nationality": "Brazil",
      "position": "Defender",
      "current_team": "Nottingham Forest Football Club",
      "market_value": 55000000,
      "fame_score": 79.85,
      "birth_year": 2002
    },
    {
      "id": 316264,
      "name": "Martin Ødegaard",
      "nationality": "Norway",
      "position": "Midfield",
      "current_team": "Arsenal Football Club",
      "market_value": 75000000,
      "fame_score": 79.84,
      "birth_year": 1998
    },
    {
      "id": 181767,
      "name": "Marquinhos",
      "nationality": "Brazil",
      "position": "Defender",
      "current_team": "Paris Saint-Germain Football Club",
      "market_value": 35000000,
      "fame_score": 79.83,
      "birth_year": 2003
    },
    {
      "id": 668268,
      "name": "Marquinhos",
      "nationality": "Brazil",
      "position": "Attack",
      "current_team": "Cruzeiro",
      "market_value": 8000000,
      "fame_score": 79.83,
      "birth_year": 2003
    },
    {
      "id": 357662,
      "name": "Declan Rice",
      "nationality": "England",
      "position": "Midfield",
      "current_team": "Arsenal Football Club",
      "market_value": 120000000,
      "fame_score": 79.76,
      "birth_year": 1999
    },
    {
      "id": 171424,
      "name": "Riyad Mahrez",
      "nationality": null,
      "position": "Attack",
      "current_team": "Al-Ahli",
      "market_value": 15000000,
      "fame_score": 79.74,
      "birth_year": 1991
    },
    {
      "id": 1600037,
      "name": "Oliver Kahn",
      "nationality": "Germany",
      "position": "Goalkeeper",
      "current_team": "FC Bayern München",
      "market_value": 0,
      "fame_score": 79.73,
      "birth_year": 1969
    },
    {
      "id": 203460,
      "name": "Jack Grealish",
      "nationality": "England",
      "position": "Attack",
      "current_team": "Manchester City Football Club",
      "market_value": 25000000,
      "fame_score": 79.72,
      "birth_year": 1995
    },
    {
      "id": 3397,
      "name": "Paul Scholes",
      "nationality": "England",
      "position": "Midfield",
      "current_team": "Manchester United Football Club",
      "market_value": 0,
      "fame_score": 79.67,
      "birth_year": 1974
    },
    {
      "id": 58864,
      "name": "Pierre-Emerick Aubameyang",
      "nationality": "Gabon",
      "position": "Attack",
      "current_team": "Olympique de Marseille",
      "market_value": 5000000,
      "fame_score": 79.64,
      "birth_year": 1989
    },
    {
      "id": 182712,
      "name": "João Cancelo",
      "nationality": "Portugal",
      "position": "Defender",
      "current_team": "Al-Hilal",
      "market_value": 20000000,
      "fame_score": 79.64,
      "birth_year": 1994
    },
    {
      "id": 19726,
      "name": "Nemanja Vidic‎",
      "nationality": "Serbia",
      "position": "Defender",
      "current_team": "Football Club Internazionale Milano S.p.A.",
      "market_value": 0,
      "fame_score": 79.61,
      "birth_year": 1981
    },
    {
      "id": 37666,
      "name": "Arturo Vidal",
      "nationality": "Chile",
      "position": "Midfield",
      "current_team": "Csd Colo-Colo",
      "market_value": 700000,
      "fame_score": 79.56,
      "birth_year": 1987
    },
    {
      "id": 598577,
      "name": "Florian Wirtz",
      "nationality": "Germany",
      "position": "Midfield",
      "current_team": "Liverpool Football Club",
      "market_value": 110000000,
      "fame_score": 79.56,
      "birth_year": 2003
    },
    {
      "id": 435338,
      "name": "Gabriel Magalhães",
      "nationality": "Brazil",
      "position": "Defender",
      "current_team": "Arsenal Football Club",
      "market_value": 75000000,
      "fame_score": 79.54,
      "birth_year": 1997
    },
    {
      "id": 462250,
      "name": "João Félix",
      "nationality": "Portugal",
      "position": "Attack",
      "current_team": "Al-Nassr",
      "market_value": 32000000,
      "fame_score": 79.53,
      "birth_year": 1999
    },
    {
      "id": 309400,
      "name": "Kai Havertz",
      "nationality": "Germany",
      "position": "Attack",
      "current_team": "Arsenal Football Club",
      "market_value": 55000000,
      "fame_score": 79.49,
      "birth_year": 1999
    },
    {
      "id": 82442,
      "name": "Olivier Giroud",
      "nationality": "France",
      "position": "Attack",
      "current_team": "Lille Olympique Sporting Club",
      "market_value": 1500000,
      "fame_score": 79.47,
      "birth_year": 1986
    },
    {
      "id": 258004,
      "name": "Rúben Dias",
      "nationality": "Portugal",
      "position": "Defender",
      "current_team": "Manchester City Football Club",
      "market_value": 60000000,
      "fame_score": 79.47,
      "birth_year": 1997
    },
    {
      "id": 1600038,
      "name": "Yaya Toure",
      "nationality": "Cote d'Ivoire",
      "position": "Midfield",
      "current_team": "Qingdao Huanghai",
      "market_value": 0,
      "fame_score": 79.47,
      "birth_year": 1983
    }
  ]
}