{
 "sweep": "full2026",
 "batch": 3,
 "players": [
  {
   "id": 183288,
   "name": "Luke Shaw",
   "current_team": "Manchester United Football Club",
   "league": "Premier League",
   "status": null,
   "nationality": "England",
   "position": "Defender",
   "market_value": 10000000,
   "fame": 61.9
  },
  {
   "id": 918969,
   "name": "Lamine Camara",
   "current_team": "Association sportive de Monaco Football Club",
   "league": "Ligue 1",
   "status": null,
   "nationality": "Senegal",
   "position": "Midfield",
   "market_value": 10000000,
   "fame": 61.9
  },
  {
   "id": 617081,
   "name": "Diego L\u00f3pez",
   "current_team": "Valencia Club de F\u00fatbol S. A. D.",
   "league": "La Liga",
   "status": null,
   "nationality": "Spain",
   "position": "Attack",
   "market_value": 15000000,
   "fame": 61.9
  },
  {
   "id": 645686,
   "name": "Lamare Bogarde",
   "current_team": "Aston Villa Football Club",
   "league": "Premier League",
   "status": null,
   "nationality": "Netherlands",
   "position": "Midfield",
   "market_value": 12000000,
   "fame": 61.8
  },
  {
   "id": 557459,
   "name": "Micky van de Ven",
   "current_team": "Tottenham Hotspur Football Club",
   "league": "Premier League",
   "status": null,
   "nationality": "Netherlands",
   "position": "Defender",
   "market_value": 65000000,
   "fame": 61.8
  },
  {
   "id": 1004834,
   "name": "George Ilenikhena",
   "current_team": "Association sportive de Monaco Football Club",
   "league": "Ligue 1",
   "status": null,
   "nationality": "Nigeria",
   "position": "Attack",
   "market_value": 10000000,
   "fame": 61.8
  },
  {
   "id": 711976,
   "name": "Andy Diouf",
   "current_team": "Football Club Internazionale Milano S.p.A.",
   "league": "Serie A",
   "status": null,
   "nationality": "France",
   "position": "Midfield",
   "market_value": 18000000,
   "fame": 61.8
  },
  {
   "id": 1071596,
   "name": "Dro Fern\u00e1ndez",
   "current_team": "Paris Saint-Germain Football Club",
   "league": "Ligue 1",
   "status": null,
   "nationality": "Spain",
   "position": "Midfield",
   "market_value": 10000000,
   "fame": 61.8
  },
  {
   "id": 387106,
   "name": "Lovro Majer",
   "current_team": "Verein f\u00fcr Leibes\u00fcbungen Wolfsburg",
   "league": "Bundesliga",
   "status": null,
   "nationality": "Croatia",
   "position": "Midfield",
   "market_value": 17000000,
   "fame": 61.8
  },
  {
   "id": 449592,
   "name": "Cameron Puertas",
   "current_team": "Sportverein Werder Bremen von 1899",
   "league": "Bundesliga",
   "status": null,
   "nationality": "Spain",
   "position": "Midfield",
   "market_value": 15000000,
   "fame": 61.8
  },
  {
   "id": 684210,
   "name": "Jaidon Anthony",
   "current_team": "Burnley Football Club",
   "league": "Premier League",
   "status": null,
   "nationality": "England",
   "position": "Attack",
   "market_value": 15000000,
   "fame": 61.8
  },
  {
   "id": 581669,
   "name": "CJ Egan-Riley",
   "current_team": "Olympique de Marseille",
   "league": "Ligue 1",
   "status": null,
   "nationality": "England",
   "position": "Defender",
   "market_value": 15000000,
   "fame": 61.8
  },
  {
   "id": 251664,
   "name": "Ivan Toney",
   "current_team": "Al-Ahli Sfc",
   "league": "Premier League",
   "status": null,
   "nationality": "England",
   "position": "Attack",
   "market_value": 50000000,
   "fame": 61.7
  },
  {
   "id": 671649,
   "name": "\u00c1lvaro Djal\u00f3",
   "current_team": "Athletic Club Bilbao",
   "league": "La Liga",
   "status": null,
   "nationality": "Guinea-Bissau",
   "position": "Attack",
   "market_value": 15000000,
   "fame": 61.7
  },
  {
   "id": 953901,
   "name": "Santiago Mouri\u00f1o",
   "current_team": "Villarreal Club de F\u00fatbol S.A.D.",
   "league": "La Liga",
   "status": null,
   "nationality": "Uruguay",
   "position": "Defender",
   "market_value": 10000000,
   "fame": 61.7
  },
  {
   "id": 1045123,
   "name": "Trey Nyoni",
   "current_team": "Liverpool Football Club",
   "league": "Premier League",
   "status": null,
   "nationality": "England",
   "position": "Midfield",
   "market_value": 6000000,
   "fame": 61.7
  },
  {
   "id": 380598,
   "name": "Santi Comesa\u00f1a",
   "current_team": "Villarreal Club de F\u00fatbol S.A.D.",
   "league": "La Liga",
   "status": null,
   "nationality": "Spain",
   "position": "Midfield",
   "market_value": 8000000,
   "fame": 61.7
  },
  {
   "id": 746695,
   "name": "Kamaldeen Sulemana",
   "current_team": "Atalanta Bergamasca Calcio S.p.a.",
   "league": "Serie A",
   "status": null,
   "nationality": "Ghana",
   "position": "Attack",
   "market_value": 20000000,
   "fame": 61.7
  },
  {
   "id": 424204,
   "name": "Alphonso Davies",
   "current_team": "FC Bayern M\u00fcnchen",
   "league": "Bundesliga",
   "status": null,
   "nationality": "Canada",
   "position": "Defender",
   "market_value": 50000000,
   "fame": 61.7
  },
  {
   "id": 616369,
   "name": "Ander Barrenetxea",
   "current_team": "Real Sociedad de F\u00fatbol S.A.D.",
   "league": "La Liga",
   "status": null,
   "nationality": "Spain",
   "position": "Attack",
   "market_value": 20000000,
   "fame": 61.7
  },
  {
   "id": 515544,
   "name": "Trai Hume",
   "current_team": "Sunderland Association Football Club",
   "league": "Premier League",
   "status": null,
   "nationality": "Northern Ireland",
   "position": "Defender",
   "market_value": 18000000,
   "fame": 61.7
  },
  {
   "id": 575998,
   "name": "Leonardo Balerdi",
   "current_team": "Olympique de Marseille",
   "league": "Ligue 1",
   "status": null,
   "nationality": "Argentina",
   "position": "Defender",
   "market_value": 20000000,
   "fame": 61.7
  },
  {
   "id": 344069,
   "name": "Anton Stach",
   "current_team": "Leeds United Association Football Club",
   "league": "Premier League",
   "status": null,
   "nationality": "Germany",
   "position": "Midfield",
   "market_value": 20000000,
   "fame": 61.7
  },
  {
   "id": 669380,
   "name": "Konstantinos Koulierakis",
   "current_team": "Verein f\u00fcr Leibes\u00fcbungen Wolfsburg",
   "league": "Bundesliga",
   "status": null,
   "nationality": "Greece",
   "position": "Defender",
   "market_value": 8000000,
   "fame": 61.7
  },
  {
   "id": 293569,
   "name": "Josh Brownhill",
   "current_team": "Al Shabab",
   "league": "Premier League",
   "status": null,
   "nationality": "England",
   "position": "Midfield",
   "market_value": 15000000,
   "fame": 61.6
  },
  {
   "id": 399434,
   "name": "Marcus Tavernier",
   "current_team": "Association Football Club Bournemouth",
   "league": "Premier League",
   "status": null,
   "nationality": "England",
   "position": "Midfield",
   "market_value": 20000000,
   "fame": 61.6
  },
  {
   "id": 398402,
   "name": "Sam Surridge",
   "current_team": "Nashville Sc",
   "league": "Premier League",
   "status": null,
   "nationality": "England",
   "position": "Attack",
   "market_value": 5500000,
   "fame": 61.6
  },
  {
   "id": 229006,
   "name": "Franck Honorat",
   "current_team": "Borussia Verein f\u00fcr Leibes\u00fcbungen 1900 M\u00f6nchengladbach",
   "league": "Bundesliga",
   "status": null,
   "nationality": "France",
   "position": "Attack",
   "market_value": 12000000,
   "fame": 61.6
  },
  {
   "id": 417346,
   "name": "Jack Harrison",
   "current_team": "Associazione Calcio Fiorentina",
   "league": "Serie A",
   "status": null,
   "nationality": "England",
   "position": "Attack",
   "market_value": 10000000,
   "fame": 61.6
  },
  {
   "id": 453870,
   "name": "Benedict Hollerbach",
   "current_team": "1. Fu\u00dfball- und Sportverein Mainz 05",
   "league": "Bundesliga",
   "status": null,
   "nationality": "Germany",
   "position": "Attack",
   "market_value": 12000000,
   "fame": 61.6
  },
  {
   "id": 346483,
   "name": "Mason Mount",
   "current_team": "Manchester United Football Club",
   "league": "Premier League",
   "status": null,
   "nationality": "England",
   "position": "Midfield",
   "market_value": 32000000,
   "fame": 61.6
  },
  {
   "id": 272642,
   "name": "Allan Saint-Maximin",
   "current_team": "Cf Am\u00e9rica",
   "league": "Premier League",
   "status": null,
   "nationality": "France",
   "position": "Attack",
   "market_value": 24000000,
   "fame": 61.6
  },
  {
   "id": 159372,
   "name": "Felipe Anderson",
   "current_team": "Palmeiras",
   "league": "Serie A",
   "status": null,
   "nationality": "Brazil",
   "position": "Attack",
   "market_value": 8000000,
   "fame": 61.5
  },
  {
   "id": 453016,
   "name": "Anthony Caci",
   "current_team": "1. Fu\u00dfball- und Sportverein Mainz 05",
   "league": "Bundesliga",
   "status": null,
   "nationality": "France",
   "position": "Defender",
   "market_value": 12000000,
   "fame": 61.5
  },
  {
   "id": 352041,
   "name": "Lucas Perri",
   "current_team": "Leeds United Association Football Club",
   "league": "Premier League",
   "status": null,
   "nationality": "Brazil",
   "position": "Goalkeeper",
   "market_value": 16000000,
   "fame": 61.5
  },
  {
   "id": 181378,
   "name": "Ga\u00ebtan Laborde",
   "current_team": "Al-Diraiyah Fc",
   "league": "Ligue 1",
   "status": null,
   "nationality": "France",
   "position": "Attack",
   "market_value": 10000000,
   "fame": 61.5
  },
  {
   "id": 282429,
   "name": "Sergio Reguil\u00f3n",
   "current_team": "Brentford Football Club",
   "league": "Premier League",
   "status": null,
   "nationality": "Spain",
   "position": "Defender",
   "market_value": 12000000,
   "fame": 61.5
  },
  {
   "id": 741257,
   "name": "\u00c1lex Jim\u00e9nez",
   "current_team": "Association Football Club Bournemouth",
   "league": "Premier League",
   "status": null,
   "nationality": "Spain",
   "position": "Defender",
   "market_value": 18000000,
   "fame": 61.5
  },
  {
   "id": 318508,
   "name": "Olivier Boscagli",
   "current_team": "Brighton and Hove Albion Football Club",
   "league": "Premier League",
   "status": null,
   "nationality": "France",
   "position": "Defender",
   "market_value": 18000000,
   "fame": 61.5
  },
  {
   "id": 324795,
   "name": "Mahdi Camara",
   "current_team": "Stade Rennais Football Club",
   "league": "Ligue 1",
   "status": null,
   "nationality": "France",
   "position": "Midfield",
   "market_value": 9000000,
   "fame": 61.5
  },
  {
   "id": 557613,
   "name": "Quentin Merlin",
   "current_team": "Stade Rennais Football Club",
   "league": "Ligue 1",
   "status": null,
   "nationality": "France",
   "position": "Defender",
   "market_value": 15000000,
   "fame": 61.5
  },
  {
   "id": 258,
   "name": "Gerald Asamoah",
   "current_team": "FC Schalke 04",
   "league": "Bundesliga",
   "status": null,
   "nationality": "Germany",
   "position": "Attack",
   "market_value": 100000,
   "fame": 61.5
  },
  {
   "id": 840149,
   "name": "Matija Frigan",
   "current_team": "Parma Calcio 1913",
   "league": "Serie A",
   "status": null,
   "nationality": "Croatia",
   "position": "Attack",
   "market_value": 7500000,
   "fame": 61.5
  },
  {
   "id": 485963,
   "name": "Pape Gueye",
   "current_team": "Villarreal Club de F\u00fatbol S.A.D.",
   "league": "La Liga",
   "status": null,
   "nationality": "Senegal",
   "position": "Midfield",
   "market_value": 20000000,
   "fame": 61.5
  },
  {
   "id": 624037,
   "name": "Joris Chotard",
   "current_team": "Stade brestois 29",
   "league": "Ligue 1",
   "status": null,
   "nationality": "France",
   "position": "Midfield",
   "market_value": 6000000,
   "fame": 61.5
  },
  {
   "id": 596153,
   "name": "Justin Njinmah",
   "current_team": "Sportverein Werder Bremen von 1899",
   "league": "Bundesliga",
   "status": null,
   "nationality": "Germany",
   "position": "Attack",
   "market_value": 7000000,
   "fame": 61.5
  },
  {
   "id": 1067904,
   "name": "Bazoumana Tour\u00e9",
   "current_team": "Turn- und Sportgemeinschaft 1899 Hoffenheim Fu\u00dfball-Spielbetriebs",
   "league": "Bundesliga",
   "status": null,
   "nationality": "Cote d'Ivoire",
   "position": "Attack",
   "market_value": 9000000,
   "fame": 61.5
  },
  {
   "id": 353366,
   "name": "Benjamin Pavard",
   "current_team": "Olympique de Marseille",
   "league": "Ligue 1",
   "status": null,
   "nationality": "France",
   "position": "Defender",
   "market_value": 20000000,
   "fame": 61.4
  },
  {
   "id": 371021,
   "name": "Arijanet Muri\u0107",
   "current_team": "Unione Sportiva Sassuolo Calcio",
   "league": "Serie A",
   "status": null,
   "nationality": "Kosovo",
   "position": "Goalkeeper",
   "market_value": 7500000,
   "fame": 61.4
  },
  {
   "id": 426192,
   "name": "Ben Brereton D\u00edaz",
   "current_team": "Southampton FC",
   "league": "Premier League",
   "status": null,
   "nationality": "Chile",
   "position": "Attack",
   "market_value": 8000000,
   "fame": 61.4
  },
  {
   "id": 451276,
   "name": "Dominik Szoboszlai",
   "current_team": "Liverpool Football Club",
   "league": "Premier League",
   "status": null,
   "nationality": "Hungary",
   "position": "Midfield",
   "market_value": 85000000,
   "fame": 61.4
  },
  {
   "id": 59016,
   "name": "David Alaba",
   "current_team": "Real Madrid Club de F\u00fatbol",
   "league": "La Liga",
   "status": null,
   "nationality": "Austria",
   "position": "Defender",
   "market_value": 20000000,
   "fame": 61.4
  },
  {
   "id": 518505,
   "name": "Jamie Leweling",
   "current_team": "Verein f\u00fcr Bewegungsspiele Stuttgart 1893",
   "league": "Bundesliga",
   "status": null,
   "nationality": "Germany",
   "position": "Attack",
   "market_value": 20000000,
   "fame": 61.4
  },
  {
   "id": 659459,
   "name": "Carney Chukwuemeka",
   "current_team": "Borussia Dortmund",
   "league": "Bundesliga",
   "status": null,
   "nationality": "England",
   "position": "Midfield",
   "market_value": 18000000,
   "fame": 61.4
  },
  {
   "id": 290249,
   "name": "Mauro Arambarri",
   "current_team": "Getafe Club de F\u00fatbol S. A. D. Team Dubai",
   "league": "La Liga",
   "status": null,
   "nationality": "Uruguay",
   "position": "Midfield",
   "market_value": 10000000,
   "fame": 61.4
  },
  {
   "id": 543387,
   "name": "Cheick Doucour\u00e9",
   "current_team": "Crystal Palace Football Club",
   "league": "Premier League",
   "status": null,
   "nationality": "Mali",
   "position": "Midfield",
   "market_value": 15000000,
   "fame": 61.4
  },
  {
   "id": 338668,
   "name": "Senne Lynen",
   "current_team": "Sportverein Werder Bremen von 1899",
   "league": "Bundesliga",
   "status": null,
   "nationality": "Belgium",
   "position": "Midfield",
   "market_value": 9000000,
   "fame": 61.4
  },
  {
   "id": 789252,
   "name": "Bence D\u00e1rdai",
   "current_team": "Verein f\u00fcr Leibes\u00fcbungen Wolfsburg",
   "league": "Bundesliga",
   "status": null,
   "nationality": "Hungary",
   "position": "Midfield",
   "market_value": 12000000,
   "fame": 61.4
  },
  {
   "id": 370789,
   "name": "Julian Ryerson",
   "current_team": "Borussia Dortmund",
   "league": "Bundesliga",
   "status": null,
   "nationality": "Norway",
   "position": "Defender",
   "market_value": 20000000,
   "fame": 61.3
  },
  {
   "id": 1121298,
   "name": "Juma Bah",
   "current_team": "Olympique Gymnaste Club Nice C\u00f4te d'Azur",
   "league": "Ligue 1",
   "status": null,
   "nationality": "Sierra Leone",
   "position": "Defender",
   "market_value": 6000000,
   "fame": 61.3
  },
  {
   "id": 592979,
   "name": "Himad Abdelli",
   "current_team": "Olympique de Marseille",
   "league": "Ligue 1",
   "status": null,
   "nationality": "Algeria",
   "position": "Midfield",
   "market_value": 7000000,
   "fame": 61.3
  },
  {
   "id": 634131,
   "name": "Aimar Oroz",
   "current_team": "Club Atl\u00e9tico Osasuna",
   "league": "La Liga",
   "status": null,
   "nationality": "Spain",
   "position": "Midfield",
   "market_value": 9000000,
   "fame": 61.3
  },
  {
   "id": 410708,
   "name": "Pascal Struijk",
   "current_team": "Leeds United Association Football Club",
   "league": "Premier League",
   "status": null,
   "nationality": "Netherlands",
   "position": "Defender",
   "market_value": 20000000,
   "fame": 61.3
  },
  {
   "id": 257732,
   "name": "Amir Rrahmani",
   "current_team": "Societ\u00e0 Sportiva Calcio Napoli",
   "league": "Serie A",
   "status": null,
   "nationality": "Kosovo",
   "position": "Defender",
   "market_value": 15000000,
   "fame": 61.3
  },
  {
   "id": 1004301,
   "name": "J\u00e9r\u00e9my Jacquet",
   "current_team": "Stade Rennais Football Club",
   "league": "Ligue 1",
   "status": null,
   "nationality": "France",
   "position": "Defender",
   "market_value": 12000000,
   "fame": 61.3
  },
  {
   "id": 159088,
   "name": "Robert Andrich",
   "current_team": "Bayer 04 Leverkusen Fu\u00dfball",
   "league": "Bundesliga",
   "status": null,
   "nationality": "Germany",
   "position": "Midfield",
   "market_value": 9000000,
   "fame": 61.3
  },
  {
   "id": 876400,
   "name": "Simone Pafundi",
   "current_team": "Udinese Calcio",
   "league": "Serie A",
   "status": null,
   "nationality": "Italy",
   "position": "Midfield",
   "market_value": 10000000,
   "fame": 61.3
  },
  {
   "id": 1011200,
   "name": "Junior Mwanga",
   "current_team": "Racing Club de Strasbourg Alsace",
   "league": "Ligue 1",
   "status": null,
   "nationality": "France",
   "position": "Midfield",
   "market_value": 6000000,
   "fame": 61.3
  },
  {
   "id": 395693,
   "name": "Houssem Aouar",
   "current_team": "Al-Ittihad",
   "league": "Serie A",
   "status": null,
   "nationality": "Algeria",
   "position": "Midfield",
   "market_value": 10000000,
   "fame": 61.2
  },
  {
   "id": 608832,
   "name": "Merlin R\u00f6hl",
   "current_team": "Everton Football Club",
   "league": "Premier League",
   "status": null,
   "nationality": "Germany",
   "position": "Midfield",
   "market_value": 16000000,
   "fame": 61.2
  },
  {
   "id": 184573,
   "name": "Victor Lindel\u00f6f",
   "current_team": "Aston Villa Football Club",
   "league": "Premier League",
   "status": null,
   "nationality": "Sweden",
   "position": "Defender",
   "market_value": 6000000,
   "fame": 61.2
  },
  {
   "id": 480763,
   "name": "Juan Foyth",
   "current_team": "Villarreal Club de F\u00fatbol S.A.D.",
   "league": "La Liga",
   "status": null,
   "nationality": "Argentina",
   "position": "Defender",
   "market_value": 15000000,
   "fame": 61.2
  },
  {
   "id": 901019,
   "name": "Neil El Aynaoui",
   "current_team": "Associazione Sportiva Roma",
   "league": "Serie A",
   "status": null,
   "nationality": "Morocco",
   "position": "Midfield",
   "market_value": 20000000,
   "fame": 61.2
  },
  {
   "id": 533662,
   "name": "Cameron Archer",
   "current_team": "Southampton FC",
   "league": "Premier League",
   "status": null,
   "nationality": "England",
   "position": "Attack",
   "market_value": 13000000,
   "fame": 61.2
  },
  {
   "id": 240414,
   "name": "Alex Meret",
   "current_team": "Societ\u00e0 Sportiva Calcio Napoli",
   "league": "Serie A",
   "status": null,
   "nationality": "Italy",
   "position": "Goalkeeper",
   "market_value": 12000000,
   "fame": 61.2
  },
  {
   "id": 503686,
   "name": "Dan Ballard",
   "current_team": "Sunderland Association Football Club",
   "league": "Premier League",
   "status": null,
   "nationality": "Northern Ireland",
   "position": "Defender",
   "market_value": 16000000,
   "fame": 61.2
  },
  {
   "id": 255450,
   "name": "Aleksey Miranchuk",
   "current_team": "Atlanta United",
   "league": "Serie A",
   "status": null,
   "nationality": "Russia",
   "position": "Midfield",
   "market_value": 10000000,
   "fame": 61.2
  },
  {
   "id": 298976,
   "name": "Borja Mayoral",
   "current_team": "Getafe Club de F\u00fatbol S. A. D. Team Dubai",
   "league": "La Liga",
   "status": null,
   "nationality": "Spain",
   "position": "Attack",
   "market_value": 15000000,
   "fame": 61.2
  },
  {
   "id": 502722,
   "name": "Luka Sucic",
   "current_team": "Real Sociedad de F\u00fatbol S.A.D.",
   "league": "La Liga",
   "status": null,
   "nationality": "Croatia",
   "position": "Midfield",
   "market_value": 10000000,
   "fame": 61.2
  },
  {
   "id": 746891,
   "name": "Cristian Volpato",
   "current_team": "Unione Sportiva Sassuolo Calcio",
   "league": "Serie A",
   "status": null,
   "nationality": "Italy",
   "position": "Midfield",
   "market_value": 6500000,
   "fame": 61.2
  },
  {
   "id": 584769,
   "name": "Dwight McNeil",
   "current_team": "Everton Football Club",
   "league": "Premier League",
   "status": null,
   "nationality": "England",
   "position": "Attack",
   "market_value": 20000000,
   "fame": 61.2
  },
  {
   "id": 716276,
   "name": "Yerson Mosquera",
   "current_team": "Wolverhampton Wanderers Football Club",
   "league": "Premier League",
   "status": null,
   "nationality": "Colombia",
   "position": "Defender",
   "market_value": 10000000,
   "fame": 61.2
  },
  {
   "id": 935231,
   "name": "V\u00edctor Mu\u00f1oz",
   "current_team": "Club Atl\u00e9tico Osasuna",
   "league": "La Liga",
   "status": null,
   "nationality": "Spain",
   "position": "Attack",
   "market_value": 10000000,
   "fame": 61.1
  },
  {
   "id": 938146,
   "name": "Adam Aznou",
   "current_team": "Everton Football Club",
   "league": "Premier League",
   "status": null,
   "nationality": "Morocco",
   "position": "Defender",
   "market_value": 7000000,
   "fame": 61.1
  },
  {
   "id": 355628,
   "name": "Igor Zubeldia",
   "current_team": "Real Sociedad de F\u00fatbol S.A.D.",
   "league": "La Liga",
   "status": null,
   "nationality": "Spain",
   "position": "Defender",
   "market_value": 9000000,
   "fame": 61.1
  },
  {
   "id": 372246,
   "name": "Carlos Soler",
   "current_team": "Real Sociedad de F\u00fatbol S.A.D.",
   "league": "La Liga",
   "status": null,
   "nationality": "Spain",
   "position": "Midfield",
   "market_value": 8000000,
   "fame": 61.1
  },
  {
   "id": 1187629,
   "name": "Max Dowman",
   "current_team": "Arsenal Football Club",
   "league": "Premier League",
   "status": null,
   "nationality": "England",
   "position": "Attack",
   "market_value": 20000000,
   "fame": 61.1
  },
  {
   "id": 130164,
   "name": "Jordan Pickford",
   "current_team": "Everton Football Club",
   "league": "Premier League",
   "status": null,
   "nationality": "England",
   "position": "Goalkeeper",
   "market_value": 15000000,
   "fame": 61.1
  },
  {
   "id": 126414,
   "name": "Hakan \u00c7alhano\u011flu",
   "current_team": "Football Club Internazionale Milano S.p.A.",
   "league": "Serie A",
   "status": null,
   "nationality": "T\u00fcrkiye",
   "position": "Midfield",
   "market_value": 25000000,
   "fame": 61.1
  },
  {
   "id": 415912,
   "name": "Konstantinos Mavropanos",
   "current_team": "West Ham United Football Club",
   "league": "Premier League",
   "status": null,
   "nationality": "Greece",
   "position": "Defender",
   "market_value": 15000000,
   "fame": 61.1
  },
  {
   "id": 748319,
   "name": "Carlos Alcaraz",
   "current_team": "Everton Football Club",
   "league": "Premier League",
   "status": null,
   "nationality": "Argentina",
   "position": "Midfield",
   "market_value": 15000000,
   "fame": 61.1
  },
  {
   "id": 466268,
   "name": "Juan Brunetta",
   "current_team": "Tigres Uanl",
   "league": "Serie A",
   "status": null,
   "nationality": "Argentina",
   "position": "Attack",
   "market_value": 7000000,
   "fame": 61.1
  },
  {
   "id": 576028,
   "name": "Thiago Almada",
   "current_team": "Club Atl\u00e9tico de Madrid S.A.D.",
   "league": "La Liga",
   "status": null,
   "nationality": "Argentina",
   "position": "Attack",
   "market_value": 20000000,
   "fame": 61.1
  },
  {
   "id": 514285,
   "name": "Quilindschy Hartman",
   "current_team": "Burnley Football Club",
   "league": "Premier League",
   "status": null,
   "nationality": "Netherlands",
   "position": "Defender",
   "market_value": 18000000,
   "fame": 61.1
  },
  {
   "id": 1061282,
   "name": "Assane Diao",
   "current_team": "Como",
   "league": "La Liga",
   "status": null,
   "nationality": "Spain",
   "position": "Attack",
   "market_value": 12000000,
   "fame": 61.1
  },
  {
   "id": 284010,
   "name": "Robin Hack",
   "current_team": "Borussia Verein f\u00fcr Leibes\u00fcbungen 1900 M\u00f6nchengladbach",
   "league": "Bundesliga",
   "status": null,
   "nationality": "Germany",
   "position": "Attack",
   "market_value": 12000000,
   "fame": 61.1
  },
  {
   "id": 484988,
   "name": "Logan Costa",
   "current_team": "Villarreal Club de F\u00fatbol S.A.D.",
   "league": "La Liga",
   "status": null,
   "nationality": "Cape Verde",
   "position": "Defender",
   "market_value": 12000000,
   "fame": 61.1
  },
  {
   "id": 789082,
   "name": "Vanderson",
   "current_team": "Association sportive de Monaco Football Club",
   "league": "Ligue 1",
   "status": null,
   "nationality": "Brazil",
   "position": "Defender",
   "market_value": 20000000,
   "fame": 61.1
  },
  {
   "id": 391065,
   "name": "Hamed Traor\u00e9",
   "current_team": "Olympique de Marseille",
   "league": "Ligue 1",
   "status": null,
   "nationality": "Cote d'Ivoire",
   "position": "Attack",
   "market_value": 20000000,
   "fame": 61.0
  },
  {
   "id": 503482,
   "name": "Min-jae Kim",
   "current_team": "FC Bayern M\u00fcnchen",
   "league": "Bundesliga",
   "status": null,
   "nationality": "Korea, South",
   "position": "Defender",
   "market_value": 40000000,
   "fame": 61.0
  },
  {
   "id": 645774,
   "name": "Eren Dink\u00e7i",
   "current_team": "1. Fu\u00dfballclub Heidenheim 1846",
   "league": "Bundesliga",
   "status": null,
   "nationality": "T\u00fcrkiye",
   "position": "Attack",
   "market_value": 8000000,
   "fame": 61.0
  },
  {
   "id": 272999,
   "name": "Miguel Almir\u00f3n",
   "current_team": "Newcastle United Football Club",
   "league": "Premier League",
   "status": null,
   "nationality": "Paraguay",
   "position": "Attack",
   "market_value": 20000000,
   "fame": 61.0
  },
  {
   "id": 442531,
   "name": "Edouard Mendy",
   "current_team": "Al-Ahli Sfc",
   "league": "Premier League",
   "status": null,
   "nationality": "Senegal",
   "position": "Goalkeeper",
   "market_value": 10000000,
   "fame": 61
  },
  {
   "id": 448632,
   "name": "Yehvann Diouf",
   "current_team": "Olympique Gymnaste Club Nice C\u00f4te d'Azur",
   "league": "Ligue 1",
   "status": null,
   "nationality": "Senegal",
   "position": "Goalkeeper",
   "market_value": 12000000,
   "fame": 61.0
  },
  {
   "id": 140776,
   "name": "Yannick Carrasco",
   "current_team": "Al Shabab",
   "league": "La Liga",
   "status": null,
   "nationality": "Belgium",
   "position": "Attack",
   "market_value": 14000000,
   "fame": 61.0
  },
  {
   "id": 452483,
   "name": "David Affengruber",
   "current_team": "Elche Club de F\u00fatbol S.A.D.",
   "league": "La Liga",
   "status": null,
   "nationality": "Austria",
   "position": "Defender",
   "market_value": 9000000,
   "fame": 61.0
  },
  {
   "id": 569389,
   "name": "Sofiane Diop",
   "current_team": "Olympique Gymnaste Club Nice C\u00f4te d'Azur",
   "league": "Ligue 1",
   "status": null,
   "nationality": "Morocco",
   "position": "Attack",
   "market_value": 8000000,
   "fame": 61.0
  },
  {
   "id": 414908,
   "name": "Marshall Munetsi",
   "current_team": "Paris Football Club",
   "league": "Ligue 1",
   "status": null,
   "nationality": "Zimbabwe",
   "position": "Midfield",
   "market_value": 12000000,
   "fame": 61.0
  },
  {
   "id": 581674,
   "name": "Charlie Patino",
   "current_team": "Deportivo La Coruna",
   "league": "Premier League",
   "status": null,
   "nationality": "England",
   "position": "Midfield",
   "market_value": 12000000,
   "fame": 61.0
  },
  {
   "id": 527966,
   "name": "Andrei Ra\u021biu",
   "current_team": "Rayo Vallecano de Madrid S. A. D.",
   "league": "La Liga",
   "status": null,
   "nationality": "Romania",
   "position": "Defender",
   "market_value": 18000000,
   "fame": 60.9
  },
  {
   "id": 1063329,
   "name": "Andr\u00e9s Garc\u00eda",
   "current_team": "Aston Villa Football Club",
   "league": "Premier League",
   "status": null,
   "nationality": "Spain",
   "position": "Defender",
   "market_value": 7000000,
   "fame": 60.9
  },
  {
   "id": 120629,
   "name": "Alphonse Areola",
   "current_team": "West Ham United Football Club",
   "league": "Premier League",
   "status": null,
   "nationality": "France",
   "position": "Goalkeeper",
   "market_value": 7000000,
   "fame": 60.9
  },
  {
   "id": 229005,
   "name": "Abdou Diallo",
   "current_team": "Al-Duhail",
   "league": "Bundesliga",
   "status": null,
   "nationality": "Senegal",
   "position": "Defender",
   "market_value": 9000000,
   "fame": 60.9
  },
  {
   "id": 849520,
   "name": "Santiago Castro",
   "current_team": "Bologna Football Club 1909",
   "league": "Serie A",
   "status": null,
   "nationality": "Argentina",
   "position": "Attack",
   "market_value": 12000000,
   "fame": 60.9
  },
  {
   "id": 353032,
   "name": "Omar Alderete",
   "current_team": "Sunderland Association Football Club",
   "league": "Premier League",
   "status": null,
   "nationality": "Paraguay",
   "position": "Defender",
   "market_value": 12000000,
   "fame": 60.9
  },
  {
   "id": 569384,
   "name": "Lucien Agoum\u00e9",
   "current_team": "Sevilla F\u00fatbol Club S.A.D.",
   "league": "La Liga",
   "status": null,
   "nationality": "France",
   "position": "Midfield",
   "market_value": 12000000,
   "fame": 60.9
  },
  {
   "id": 1084638,
   "name": "Karim Coulibaly",
   "current_team": "Sas Epinal",
   "league": "Bundesliga",
   "status": null,
   "nationality": "Germany",
   "position": "Defender",
   "market_value": 20000000,
   "fame": 60.9
  },
  {
   "id": 257474,
   "name": "Vanja Milinkovi\u0107-Savi\u0107",
   "current_team": "Societ\u00e0 Sportiva Calcio Napoli",
   "league": "Serie A",
   "status": null,
   "nationality": "Serbia",
   "position": "Goalkeeper",
   "market_value": 18000000,
   "fame": 60.9
  },
  {
   "id": 433049,
   "name": "Youssef En-Nesyri",
   "current_team": "Fenerbahce",
   "league": "La Liga",
   "status": null,
   "nationality": "Morocco",
   "position": "Attack",
   "market_value": 20000000,
   "fame": 60.9
  },
  {
   "id": 525704,
   "name": "Nicol\u00f2 Rovella",
   "current_team": "Societ\u00e0 Sportiva Lazio S.p.A.",
   "league": "Serie A",
   "status": null,
   "nationality": "Italy",
   "position": "Midfield",
   "market_value": 18000000,
   "fame": 60.9
  }
 ]
}